uniconnapps/connector_proto/actions/v1/main_pb2.py
uniconnapps/connector_proto/actions/v1/main_pb2_grpc.py
uniconnapps/connector_proto/common/messages_pb2.py
uniconnapps/connector_proto/common/messages_pb2_grpc.py
uniconnapps/connector_proto/events/v1/main_pb2.py
uniconnapps/connector_proto/events/v1/main_pb2_grpc.py
uniconnapps_connector_proto-0.0.1a2.dist-info/LICENSE
uniconnapps_connector_proto-0.0.1a2.dist-info/METADATA
uniconnapps_connector_proto-0.0.1a2.dist-info/NOTICE
uniconnapps_connector_proto-0.0.1a2.dist-info/WHEEL
uniconnapps_connector_proto-0.0.1a2.dist-info/top_level.txt
uniconnapps_connector_proto-0.0.1a2.dist-info/RECORD
